setup.py
pyzfscore/__init__.py
pyzfscore/_cffi.py
pyzfscore/libnvpair.py
pyzfscore/utils.py
pyzfscore/zfs.py
pyzfscore.egg-info/PKG-INFO
pyzfscore.egg-info/SOURCES.txt
pyzfscore.egg-info/dependency_links.txt
pyzfscore.egg-info/not-zip-safe
pyzfscore.egg-info/top_level.txt
pyzfscore/__pycache__/_cffi__x8618e7c5xe2b6f166.c
pyzfscore/__pycache__/_cffi__xea27abcaxc1e1bc38.c
pyzfscore/flufl/__init__.py
pyzfscore/flufl/enum/__init__.py
pyzfscore/flufl/enum/_enum.py
pyzfscore/flufl/enum/conf.py
pyzfscore/libzfs/__init__.py
pyzfscore/libzfs/_cffi.py
pyzfscore/libzfs/consts.py
pyzfscore/libzfs/czfs.py