Metadata-Version: 1.0
Name: pyzfscore
Version: 0.0.2
Summary: ZFS CFFI wrapper.
Home-page: http://github.com/wengole/pyzfscore
Author: Ben Cole
Author-email: wengole@gmail.com
License: GPL3
Platform: UNKNOWN
